{
  "sheet_name": "sbe36",
  "amount_header": {
    "Gross": 9892.87,
    "Recoveries": -2.0,
    "Receipts": 0.0,
    "Net": 9890.87
  },
  "header": [
    "Ministry of Finance",
    "Demand No. 36",
    "Direct Taxes"
  ],
  "header_sec": {
    "start": 8,
    "end": 11
  },
  "sections": [
    {
      "name": "A",
      "start": 12,
      "end": 37
    },
    {
      "name": "B",
      "start": 37,
      "end": 47
    }
  ],
  "amount_cols": [
    "Unnamed: 15",
    "Unnamed: 17",
    "Unnamed: 19",
    "Unnamed: 21",
    "Unnamed: 23",
    "Unnamed: 25",
    "Unnamed: 29",
    "Unnamed: 31",
    "Unnamed: 33",
    "Unnamed: 35",
    "Unnamed: 39",
    "Unnamed: 41"
  ],
  "amount_heads": [
    {
      "head": [
        "A. The Budget allocations, net of recoveries are given below:",
        "CENTRE'S EXPENDITURE",
        "Establishment Expenditure of the Centre"
      ],
      "amount": 8840.87
    },
    {
      "head": [
        "A. The Budget allocations, net of recoveries are given below:",
        "CENTRE'S EXPENDITURE",
        "Establishment Expenditure of the Centre",
        "Collection of Taxes on Income and Expenditure"
      ],
      "amount": 8075.8
    },
    {
      "head": [
        "A. The Budget allocations, net of recoveries are given below:",
        "CENTRE'S EXPENDITURE",
        "Establishment Expenditure of the Centre",
        "Collection of Taxes on Income and Expenditure",
        "Collection of Income Tax"
      ],
      "amount": 6999.03
    },
    {
      "head": [
        "A. The Budget allocations, net of recoveries are given below:",
        "CENTRE'S EXPENDITURE",
        "Establishment Expenditure of the Centre",
        "Collection of Taxes on Income and Expenditure",
        "Collection of Corporation Tax"
      ],
      "amount": 1076.77
    },
    {
      "head": [
        "A. The Budget allocations, net of recoveries are given below:",
        "CENTRE'S EXPENDITURE",
        "Establishment Expenditure of the Centre",
        "Collection of Taxes on Wealth, Securities Transaction and other Taxes"
      ],
      "amount": 765.07
    },
    {
      "head": [
        "A. The Budget allocations, net of recoveries are given below:",
        "CENTRE'S EXPENDITURE",
        "Establishment Expenditure of the Centre",
        "Collection of Taxes on Wealth, Securities Transaction and other Taxes",
        "Collection of Wealth Tax"
      ],
      "amount": 20.71
    },
    {
      "head": [
        "A. The Budget allocations, net of recoveries are given below:",
        "CENTRE'S EXPENDITURE",
        "Establishment Expenditure of the Centre",
        "Collection of Taxes on Wealth, Securities Transaction and other Taxes",
        "Securities Transaction Tax"
      ],
      "amount": 41.41
    },
    {
      "head": [
        "A. The Budget allocations, net of recoveries are given below:",
        "CENTRE'S EXPENDITURE",
        "Establishment Expenditure of the Centre",
        "Collection of Taxes on Wealth, Securities Transaction and other Taxes",
        "Collection of Other Taxes"
      ],
      "amount": 144.95
    },
    {
      "head": [
        "A. The Budget allocations, net of recoveries are given below:",
        "CENTRE'S EXPENDITURE",
        "Establishment Expenditure of the Centre",
        "Collection of Taxes on Wealth, Securities Transaction and other Taxes",
        "Purchase of Ready Built Accommodation - Office Buildings"
      ],
      "amount": 466.2
    },
    {
      "head": [
        "A. The Budget allocations, net of recoveries are given below:",
        "CENTRE'S EXPENDITURE",
        "Establishment Expenditure of the Centre",
        "Collection of Taxes on Wealth, Securities Transaction and other Taxes",
        "Purchase of Ready Built Accommodation - Residential Buildings"
      ],
      "amount": 91.8
    },
    {
      "head": [
        "A. The Budget allocations, net of recoveries are given below:",
        "CENTRE'S EXPENDITURE",
        "Other Central Sector Expenditure"
      ],
      "amount": 1050
    },
    {
      "head": [
        "A. The Budget allocations, net of recoveries are given below:",
        "CENTRE'S EXPENDITURE",
        "Other Central Sector Expenditure",
        "Others"
      ],
      "amount": 1050
    },
    {
      "head": [
        "A. The Budget allocations, net of recoveries are given below:",
        "CENTRE'S EXPENDITURE",
        "Other Central Sector Expenditure",
        "Others",
        "Capital Outlay on Miscellaneous General Services"
      ],
      "amount": 1050
    },
    {
      "head": [
        "B. Developmental Head",
        "General Services"
      ],
      "amount": 9799.07
    },
    {
      "head": [
        "B. Developmental Head",
        "General Services",
        "Collection of Taxes on Income and Expenditure"
      ],
      "amount": 8075.8
    },
    {
      "head": [
        "B. Developmental Head",
        "General Services",
        "Collection of Taxes on Wealth, Securities Transaction Tax and Other Taxes"
      ],
      "amount": 207.07
    },
    {
      "head": [
        "B. Developmental Head",
        "General Services",
        "Capital Outlay on Public Works"
      ],
      "amount": 466.2
    },
    {
      "head": [
        "B. Developmental Head",
        "General Services",
        "Capital Outlay on Miscellaneous General Services"
      ],
      "amount": 1050.0
    },
    {
      "head": [
        "B. Developmental Head",
        "Social Services"
      ],
      "amount": 91.8
    },
    {
      "head": [
        "B. Developmental Head",
        "Social Services",
        "Capital Outlay on Housing"
      ],
      "amount": 91.8
    }
  ]
}